rest/__init__.py
rest/pi_rest.py
pipi_rest-1.0.0.dist-info/METADATA
pipi_rest-1.0.0.dist-info/WHEEL
pipi_rest-1.0.0.dist-info/top_level.txt
pipi_rest-1.0.0.dist-info/RECORD
