Metadata-Version: 2.1
Name: pipi-rest
Version: 1.0.0
Summary: REST supported
Home-page: https://github.com/eronrunner/pipi_rest
Author: Eron
Author-email: eron.runner@gmail.com
License: MIT
Platform: UNKNOWN
Classifier: License :: OSI Approved :: MIT License
Classifier: Programming Language :: Python :: 3
Classifier: Programming Language :: Python :: 3.7
Requires-Dist: pipi-json
